tensortrack/ModelParams.py
tensortrack/TrackExceptions.py
tensortrack/Tracker.py
tensortrack/__init__.py
tensor_track-0.0.11.dist-info/LICENSE
tensor_track-0.0.11.dist-info/METADATA
tensor_track-0.0.11.dist-info/WHEEL
tensor_track-0.0.11.dist-info/top_level.txt
tensor_track-0.0.11.dist-info/RECORD
