Metadata-Version: 2.1
Name: tensor-track
Version: 0.0.11
Summary: The one-stop shop for tracking TensorFlow metrics
Home-page: https://github.com/SamClaflin/Tensor-Track
Author: Sam Claflin
Author-email: samclaflin7@gmail.com
License: MIT
Platform: UNKNOWN
